Workbook

Sheet Company_Info
B3: Fields | C3: Details
B4: Company Name | C4: DesertTech Trading LLC
B5: Country | C5: United Arab Emirates
B6: Emirate | C6: Dubai
B7: Business Type | C7: IT Equipment Trading
B8: Currency | C8: AED
B9: VAT Registration Status | C9: VAT Registered
B10: Standard VAT Rate Used | C10: 0.05
B11: Project Period | C11: January 2026 - March 2026
B12: Project Type | C12: Simulated Portfolio Project

Sheet Dashboard
B2: DesertTech Trading LLC
A5: Total Sales | D5: Output VAT | G5: Input VAT | J5: Net VAT Position
A6: =SUMIFS(tblTransactions[Amount Before VAT],tblTransactions[Type],"Sale") -> 2416000 | D6: =VAT_Summary!C5 -> 120800 | G6: =VAT_Summary!E5 -> 159450 | J6: =D6-G6 -> -38650
J8: Type | K8: Sale
B10: Month | C10: Sales | D10: Output VAT | E10: Input VAT | G10: Payment Status | H10: Amount | J10: Row Labels | K10: Sum of Amount Before VAT
B11: 46023 | C11: =VAT_Summary!B2 -> 435000 | D11: =VAT_Summary!C2 -> 21750 | E11: =VAT_Summary!E2 -> 66900 | G11: Paid | H11: =SUMIFS(Transactions!I:I,Transactions!C:C,"Sale",Transactions!M:M,"Paid") -> 2021000 | J11: Accessories | K11: 940000
B12: 46054 | C12: =VAT_Summary!B3 -> 785000 | D12: =VAT_Summary!C3 -> 39250 | E12: =VAT_Summary!E3 -> 32000 | G12: Pending | H12: =SUMIFS(Transactions!I:I,Transactions!C:C,"Sale",Transactions!M:M,"Pending") -> 395000 | J12: Computer | K12: 870000
B13: 46082 | C13: =VAT_Summary!B4 -> 1196000 | D13: =VAT_Summary!C4 -> 59800 | E13: =VAT_Summary!E4 -> 60550 | J13: Display | K13: 606000
J14: Grand Total | K14: 2416000

Sheet Transactions
A1: Transaction ID | B1: Date | C1: Type | D1: Customer/Supplier | E1: Description | F1: Category | G1: Quantity | H1: Unit Price(AED) | I1: Amount Before VAT | J1: VAT Rate | K1: VAT Amount | L1: Total Amount | M1: Payment Status | N1: VAT Treatment | O1: Month | P1: Notes
A2: T001 | B2: 46027 | C2: Sale | E2: Laptop | F2: Computer | G2: 5 | H2: 25000 | I2: =H2*G2 -> 125000 | J2: 0.05 | K2: =I2*J2 -> 6250 | L2: =I2+K2 -> 131250 | M2: Paid | N2: Standard Rated | O2: =TEXT(tblTransactions[[#This Row],[Date]],"mmm-yyyy") -> Jan-2026
A3: T002 | B3: 46030 | C3: Purchase | E3: Laptop | F3: Computer | G3: 10 | H3: 40000 | I3: =H3*G3 -> 400000 | J3: 0.05 | K3: =I3*J3 -> 20000 | L3: =I3+K3 -> 420000 | M3: Paid | N3: Standard Rated | O3: =TEXT(tblTransactions[[#This Row],[Date]],"mmm-yyyy") -> Jan-2026
A4: T003 | B4: 46034 | C4: Sale | E4: Monitors | F4: Display | G4: 10 | H4: 15000 | I4: =H4*G4 -> 150000 | J4: 0.05 | K4: =I4*J4 -> 7500 | L4: =I4+K4 -> 157500 | M4: Pending | N4: Standard Rated | O4: =TEXT(tblTransactions[[#This Row],[Date]],"mmm-yyyy") -> Jan-2026
A5: T004 | B5: 46037 | C5: Purchase | E5: Monitors | F5: Display | G5: 15 | H5: 22000 | I5: =H5*G5 -> 330000 | J5: 0.05 | K5: =I5*J5 -> 16500 | L5: =I5+K5 -> 346500 | M5: Paid | N5: Standard Rated | O5: =TEXT(tblTransactions[[#This Row],[Date]],"mmm-yyyy") -> Jan-2026
A6: T005 | B6: 46040 | C6: Expense | E6: Office Supplies | F6: Office | G6: 1 | H6: 3000 | I6: =H6*G6 -> 3000 | J6: 0.05 | K6: =I6*J6 -> 150 | L6: =I6+K6 -> 3150 | M6: Paid | N6: Standard Rated | O6: =TEXT(tblTransactions[[#This Row],[Date]],"mmm-yyyy") -> Jan-2026
A7: T006 | B7: 46043 | C7: Sale | E7: Accessories | F7: Accessories | G7: 20 | H7: 8000 | I7: =H7*G7 -> 160000 | J7: 0.05 | K7: =I7*J7 -> 8000 | L7: =I7+K7 -> 168000 | M7: Paid | N7: Standard Rated | O7: =TEXT(tblTransactions[[#This Row],[Date]],"mmm-yyyy") -> Jan-2026
A8: T007 | B8: 46046 | C8: Purchase | E8: Accessories | F8: Accessories | G8: 50 | H8: 12000 | I8: =H8*G8 -> 600000 | J8: 0.05 | K8: =I8*J8 -> 30000 | L8: =I8+K8 -> 630000 | M8: Pending | N8: Standard Rated | O8: =TEXT(tblTransactions[[#This Row],[Date]],"mmm-yyyy") -> Jan-2026
A9: T008 | B9: 46049 | C9: Expense | E9: Advertising | F9: Marketing | G9: 1 | H9: 5000 | I9: =H9*G9 -> 5000 | J9: 0.05 | K9: =I9*J9 -> 250 | L9: =I9+K9 -> 5250 | M9: Paid | N9: Standard Rated | O9: =TEXT(tblTransactions[[#This Row],[Date]],"mmm-yyyy") -> Jan-2026
A10: T009 | B10: 46056 | C10: Sale | E10: Laptop | F10: Computer | G10: 7 | H10: 35000 | I10: =H10*G10 -> 245000 | J10: 0.05 | K10: =I10*J10 -> 12250 | L10: =I10+K10 -> 257250 | M10: Pending | N10: Standard Rated | O10: =TEXT(tblTransactions[[#This Row],[Date]],"mmm-yyyy") -> Feb-2026
A11: T010 | B11: 46059 | C11: Purchase | E11: Laptop | F11: Computer | G11: 6 | H11: 30000 | I11: =H11*G11 -> 180000 | J11: 0.05 | K11: =I11*J11 -> 9000 | L11: =I11+K11 -> 189000 | M11: Paid | N11: Standard Rated | O11: =TEXT(tblTransactions[[#This Row],[Date]],"mmm-yyyy") -> Feb-2026
A12: T011 | B12: 46063 | C12: Sale | E12: Monitors | F12: Display | G12: 12 | H12: 20000 | I12: =H12*G12 -> 240000 | J12: 0.05 | K12: =I12*J12 -> 12000 | L12: =I12+K12 -> 252000 | M12: Paid | N12: Standard Rated | O12: =TEXT(tblTransactions[[#This Row],[Date]],"mmm-yyyy") -> Feb-2026
A13: T012 | B13: 46067 | C13: Expense | E13: Office Equipments | F13: Office | G13: 1 | H13: 10000 | I13: =H13*G13 -> 10000 | J13: 0.05 | K13: =I13*J13 -> 500 | L13: =I13+K13 -> 10500 | M13: Pending | N13: Standard Rated | O13: =TEXT(tblTransactions[[#This Row],[Date]],"mmm-yyyy") -> Feb-2026
... A21: T020 | B21: 46106 | C21: Sale | E21: Accessories | F21: Accessories | G21: 30 | H21: 16000 | I21: =H21*G21 -> 480000 | J21: 0.05 | K21: =I21*J21 -> 24000 | L21: =I21+K21 -> 504000 | M21: Paid | N21: Standard Rated | O21: =TEXT(tblTransactions[[#This Row],[Date]],"mmm-yyyy") -> Mar-2026

Sheet Customers
A2: Customer ID | B2: Customer Name | C2: Emirate
A3: C001 | B3: Dubai Business Sollutions LLC | C3: Dubai
A4: C002 | B4: Gulff Office Supplies LLC | C4: Sharjah
A5: C003 | B5: Al Noor Technologies LLC | C5: Abu Dhabi
A6: C004 | B6: Marina Digital LLC | C6: Dubai
A7: C005 | B7: Falcon It Services LLC | C7: Ajman

Sheet Suppliers
A2: Supplier ID | B2: Suppllier Name | C2: Emirate
A3: S001 | B3: Emirates Computer Trading LLC | C3: Dubai
A4: S002 | B4: Gulf Electronics Trading LLC | C4: Sharjah
A5: S003 | B5: TechSource Middle East LLC | C5: Dubai
A6: S004 | B6: OfficePro Supplies LLC | C6: Abu Dhabi
A7: S005 | B7: Digital Accessories Trading LLC | C7: Dubai

Sheet VAT_Summary
A1: Month | B1: Sales Before VAT | C1: Output VAT | D1: Purchase&Expenses Before VAT | E1: Input Vat | F1: Net VAT
A2: 46023 | B2: =SUMIFS(tblTransactions[Amount Before VAT],tblTransactions[Month],A2,tblTransactions[Type],"Sale") -> 435000 | C2: =SUMIFS(tblTransactions[VAT Amount],tblTransactions[Month],A2,tblTransactions[Type],"Sale") -> 21750 | D2: =SUMIFS(tblTransactions[Amount Before VAT],tblTransactions[Month],A2,tblTransactions[Type],"Purchase")+SUMIFS(tblTransactions[Amount Before VAT],tblTransactions[Month],A2,tblTransactions[Type],"Expense") -> 1338000 | E2: =SUMIFS(tblTransactions[VAT Amount],tblTransactions[Month],A2,tblTransactions[Type],"Purchase")+SUMIFS(tblTransactions[VAT Amount],tblTransactions[Month],A2,tblTransactions[Type],"Expense") -> 66900 | F2: =C2-E2 -> -45150
A3: 46054 | B3: =SUMIFS(tblTransactions[Amount Before VAT],tblTransactions[Month],A3,tblTransactions[Type],"Sale") -> 785000 | C3: =SUMIFS(tblTransactions[VAT Amount],tblTransactions[Month],A3,tblTransactions[Type],"Sale") -> 39250 | D3: =SUMIFS(tblTransactions[Amount Before VAT],tblTransactions[Month],A3,tblTransactions[Type],"Purchase")+SUMIFS(tblTransactions[Amount Before VAT],tblTransactions[Month],A3,tblTransactions[Type],"Expense") -> 640000 | E3: =SUMIFS(tblTransactions[VAT Amount],tblTransactions[Month],A3,tblTransactions[Type],"Purchase")+SUMIFS(tblTransactions[VAT Amount],tblTransactions[Month],A3,tblTransactions[Type],"Expense") -> 32000 | F3: =C3-E3 -> 7250
A4: 46082 | B4: =SUMIFS(tblTransactions[Amount Before VAT],tblTransactions[Month],A4,tblTransactions[Type],"Sale") -> 1196000 | C4: =SUMIFS(tblTransactions[VAT Amount],tblTransactions[Month],A4,tblTransactions[Type],"Sale") -> 59800 | D4: =SUMIFS(tblTransactions[Amount Before VAT],tblTransactions[Month],A4,tblTransactions[Type],"Purchase")+SUMIFS(tblTransactions[Amount Before VAT],tblTransactions[Month],A4,tblTransactions[Type],"Expense") -> 1211000 | E4: =SUMIFS(tblTransactions[VAT Amount],tblTransactions[Month],A4,tblTransactions[Type],"Purchase")+SUMIFS(tblTransactions[VAT Amount],tblTransactions[Month],A4,tblTransactions[Type],"Expense") -> 60550 | F4: =C4-E4 -> -750
A5: Total | B5: =SUM(B2:B4) -> 2416000 | C5: =SUM(C2:C4) -> 120800 | D5: =SUM(D2:D4) -> 3189000 | E5: =SUM(E2:E4) -> 159450 | F5: =SUM(F2:F4) -> -38650

Sheet VAT_Reconciliation
A1: Check | B1: Transaction Register | C1: VAT Summary | D1: Difference | E1: Status
A2: Sales Before VAT | B2: =SUMIFS(tblTransactions[Amount Before VAT],tblTransactions[Type],"Sale") -> 2416000 | C2: =VAT_Summary!B5 -> 2416000 | D2: =B2-C2 -> 0 | E2: =IF(ABS(D2)<0.01,"OK","CHECK") -> OK
A3: Output VAT | B3: =SUMIFS(tblTransactions[VAT Amount],tblTransactions[Type],"Sale") -> 120800 | C3: =VAT_Summary!C5 -> 120800 | D3: =B3-C3 -> 0 | E3: =IF(ABS(D3)<0.01,"OK","CHECK") -> OK
A4: Purchase&Expenses Before VAT | B4: =SUMIFS(tblTransactions[Amount Before VAT],tblTransactions[Type],"Purchase")+SUMIFS(tblTransactions[Amount Before VAT],tblTransactions[Type],"Expense") -> 3189000 | C4: =VAT_Summary!D5 -> 3189000 | D4: =B4-C4 -> 0 | E4: =IF(ABS(D4)<0.01,"OK","CHECK") -> OK
A5: Input VAT | B5: =SUMIFS(tblTransactions[VAT Amount],tblTransactions[Type],"Purchase")+SUMIFS(tblTransactions[VAT Amount],tblTransactions[Type],"Expense") -> 159450 | C5: =VAT_Summary!E5 -> 159450 | D5: =B5-C5 -> 0 | E5: =IF(ABS(D5)<0.01,"OK","CHECK") -> OK
A6: Net VAT | B6: =B3-B5 -> -38650 | C6: =VAT_Summary!F5 -> -38650 | D6: =B6-C6 -> 0 | E6: =IF(ABS(D6)<0.01,"OK","CHECK") -> OK
